{
  "program_path": ".",
  "language": "nickel",
  "frameworks": [],
  "weak_points": [],
  "statistics": {
    "total_lines": 3374,
    "unsafe_blocks": 13,
    "panic_sites": 0,
    "unwrap_calls": 0,
    "allocation_sites": 1,
    "io_operations": 31,
    "threading_constructs": 2
  },
  "file_statistics": [
    {
      "file_path": "contractiles/trust/Trustfile.hs",
      "lines": 105,
      "unsafe_blocks": 0,
      "panic_sites": 0,
      "unwrap_calls": 0,
      "allocation_sites": 0,
      "io_operations": 1,
      "threading_constructs": 0
    },
    {
      "file_path": "ffi/zig/src/main.zig",
      "lines": 274,
      "unsafe_blocks": 0,
      "panic_sites": 0,
      "unwrap_calls": 0,
      "allocation_sites": 1,
      "io_operations": 0,
      "threading_constructs": 0
    },
    {
      "file_path": "ffi/zig/test/integration_test.zig",
      "lines": 182,
      "unsafe_blocks": 0,
      "panic_sites": 0,
      "unwrap_calls": 0,
      "allocation_sites": 0,
      "io_operations": 0,
      "threading_constructs": 2
    },
    {
      "file_path": "src/abi/Foreign.idr",
      "lines": 216,
      "unsafe_blocks": 12,
      "panic_sites": 0,
      "unwrap_calls": 0,
      "allocation_sites": 0,
      "io_operations": 0,
      "threading_constructs": 0
    },
    {
      "file_path": "src/abi/Types.idr",
      "lines": 231,
      "unsafe_blocks": 1,
      "panic_sites": 0,
      "unwrap_calls": 0,
      "allocation_sites": 0,
      "io_operations": 0,
      "threading_constructs": 0
    },
    {
      "file_path": "specs/components/policy-entitlements.k9.ncl",
      "lines": 74,
      "unsafe_blocks": 0,
      "panic_sites": 0,
      "unwrap_calls": 0,
      "allocation_sites": 0,
      "io_operations": 1,
      "threading_constructs": 0
    },
    {
      "file_path": "specs/components/graphql-schema.k9.ncl",
      "lines": 96,
      "unsafe_blocks": 0,
      "panic_sites": 0,
      "unwrap_calls": 0,
      "allocation_sites": 0,
      "io_operations": 1,
      "threading_constructs": 0
    },
    {
      "file_path": "specs/components/proof-envelope.k9.ncl",
      "lines": 50,
      "unsafe_blocks": 0,
      "panic_sites": 0,
      "unwrap_calls": 0,
      "allocation_sites": 0,
      "io_operations": 1,
      "threading_constructs": 0
    },
    {
      "file_path": "specs/components/bitemporal-store.k9.ncl",
      "lines": 43,
      "unsafe_blocks": 0,
      "panic_sites": 0,
      "unwrap_calls": 0,
      "allocation_sites": 0,
      "io_operations": 1,
      "threading_constructs": 0
    },
    {
      "file_path": "specs/components/subscription-transport.k9.ncl",
      "lines": 45,
      "unsafe_blocks": 0,
      "panic_sites": 0,
      "unwrap_calls": 0,
      "allocation_sites": 0,
      "io_operations": 1,
      "threading_constructs": 0
    },
    {
      "file_path": "specs/components/resolver-policy-gate.k9.ncl",
      "lines": 42,
      "unsafe_blocks": 0,
      "panic_sites": 0,
      "unwrap_calls": 0,
      "allocation_sites": 0,
      "io_operations": 1,
      "threading_constructs": 0
    },
    {
      "file_path": "specs/components/subscription-auth-flow.k9.ncl",
      "lines": 43,
      "unsafe_blocks": 0,
      "panic_sites": 0,
      "unwrap_calls": 0,
      "allocation_sites": 0,
      "io_operations": 1,
      "threading_constructs": 0
    },
    {
      "file_path": "specs/components/vql-mapping.k9.ncl",
      "lines": 59,
      "unsafe_blocks": 0,
      "panic_sites": 0,
      "unwrap_calls": 0,
      "allocation_sites": 0,
      "io_operations": 1,
      "threading_constructs": 0
    },
    {
      "file_path": "specs/components/osi-forensics-matrix.k9.ncl",
      "lines": 87,
      "unsafe_blocks": 0,
      "panic_sites": 0,
      "unwrap_calls": 0,
      "allocation_sites": 0,
      "io_operations": 1,
      "threading_constructs": 0
    },
    {
      "file_path": "specs/components/passive-collector.k9.ncl",
      "lines": 40,
      "unsafe_blocks": 0,
      "panic_sites": 0,
      "unwrap_calls": 0,
      "allocation_sites": 0,
      "io_operations": 1,
      "threading_constructs": 0
    },
    {
      "file_path": "specs/components/hud-module-mapping.k9.ncl",
      "lines": 53,
      "unsafe_blocks": 0,
      "panic_sites": 0,
      "unwrap_calls": 0,
      "allocation_sites": 0,
      "io_operations": 1,
      "threading_constructs": 0
    },
    {
      "file_path": "specs/components/resolver-policy-gate-impl.k9.ncl",
      "lines": 34,
      "unsafe_blocks": 0,
      "panic_sites": 0,
      "unwrap_calls": 0,
      "allocation_sites": 0,
      "io_operations": 1,
      "threading_constructs": 0
    },
    {
      "file_path": "specs/components/active-probe.k9.ncl",
      "lines": 76,
      "unsafe_blocks": 0,
      "panic_sites": 0,
      "unwrap_calls": 0,
      "allocation_sites": 0,
      "io_operations": 1,
      "threading_constructs": 0
    },
    {
      "file_path": "specs/components/alerting-retention.k9.ncl",
      "lines": 66,
      "unsafe_blocks": 0,
      "panic_sites": 0,
      "unwrap_calls": 0,
      "allocation_sites": 0,
      "io_operations": 1,
      "threading_constructs": 0
    },
    {
      "file_path": "specs/components/known-limitations.k9.ncl",
      "lines": 49,
      "unsafe_blocks": 0,
      "panic_sites": 0,
      "unwrap_calls": 0,
      "allocation_sites": 0,
      "io_operations": 1,
      "threading_constructs": 0
    },
    {
      "file_path": "specs/assemble.k9.ncl",
      "lines": 61,
      "unsafe_blocks": 0,
      "panic_sites": 0,
      "unwrap_calls": 0,
      "allocation_sites": 0,
      "io_operations": 15,
      "threading_constructs": 0
    }
  ],
  "recommended_attacks": [
    "disk",
    "cpu"
  ],
  "dependency_graph": {
    "edges": [
      {
        "from": "src/abi/Foreign.idr",
        "to": "src/abi/Types.idr",
        "relation": "shared_dir:src/abi",
        "weight": 1.0
      },
      {
        "from": "specs/components/policy-entitlements.k9.ncl",
        "to": "specs/components/graphql-schema.k9.ncl",
        "relation": "shared_dir:specs/components",
        "weight": 1.0
      },
      {
        "from": "specs/components/graphql-schema.k9.ncl",
        "to": "specs/components/proof-envelope.k9.ncl",
        "relation": "shared_dir:specs/components",
        "weight": 1.0
      },
      {
        "from": "specs/components/proof-envelope.k9.ncl",
        "to": "specs/components/bitemporal-store.k9.ncl",
        "relation": "shared_dir:specs/components",
        "weight": 1.0
      },
      {
        "from": "specs/components/bitemporal-store.k9.ncl",
        "to": "specs/components/subscription-transport.k9.ncl",
        "relation": "shared_dir:specs/components",
        "weight": 1.0
      },
      {
        "from": "specs/components/subscription-transport.k9.ncl",
        "to": "specs/components/resolver-policy-gate.k9.ncl",
        "relation": "shared_dir:specs/components",
        "weight": 1.0
      },
      {
        "from": "specs/components/resolver-policy-gate.k9.ncl",
        "to": "specs/components/subscription-auth-flow.k9.ncl",
        "relation": "shared_dir:specs/components",
        "weight": 1.0
      },
      {
        "from": "specs/components/subscription-auth-flow.k9.ncl",
        "to": "specs/components/vql-mapping.k9.ncl",
        "relation": "shared_dir:specs/components",
        "weight": 1.0
      },
      {
        "from": "specs/components/vql-mapping.k9.ncl",
        "to": "specs/components/osi-forensics-matrix.k9.ncl",
        "relation": "shared_dir:specs/components",
        "weight": 1.0
      },
      {
        "from": "specs/components/osi-forensics-matrix.k9.ncl",
        "to": "specs/components/passive-collector.k9.ncl",
        "relation": "shared_dir:specs/components",
        "weight": 1.0
      },
      {
        "from": "specs/components/passive-collector.k9.ncl",
        "to": "specs/components/hud-module-mapping.k9.ncl",
        "relation": "shared_dir:specs/components",
        "weight": 1.0
      },
      {
        "from": "specs/components/hud-module-mapping.k9.ncl",
        "to": "specs/components/resolver-policy-gate-impl.k9.ncl",
        "relation": "shared_dir:specs/components",
        "weight": 1.0
      },
      {
        "from": "specs/components/resolver-policy-gate-impl.k9.ncl",
        "to": "specs/components/active-probe.k9.ncl",
        "relation": "shared_dir:specs/components",
        "weight": 1.0
      },
      {
        "from": "specs/components/active-probe.k9.ncl",
        "to": "specs/components/alerting-retention.k9.ncl",
        "relation": "shared_dir:specs/components",
        "weight": 1.0
      },
      {
        "from": "specs/components/alerting-retention.k9.ncl",
        "to": "specs/components/known-limitations.k9.ncl",
        "relation": "shared_dir:specs/components",
        "weight": 1.0
      }
    ]
  },
  "taint_matrix": {
    "rows": []
  }
}