{
  "program_path": ".",
  "language": "nickel",
  "frameworks": [
    "Concurrent"
  ],
  "weak_points": [],
  "statistics": {
    "total_lines": 6500,
    "unsafe_blocks": 13,
    "panic_sites": 0,
    "unwrap_calls": 4,
    "allocation_sites": 17,
    "io_operations": 8,
    "threading_constructs": 2
  },
  "file_statistics": [
    {
      "file_path": "src/main.rs",
      "lines": 1296,
      "unsafe_blocks": 0,
      "panic_sites": 0,
      "unwrap_calls": 4,
      "allocation_sites": 6,
      "io_operations": 2,
      "threading_constructs": 0
    },
    {
      "file_path": "src/metadata.rs",
      "lines": 269,
      "unsafe_blocks": 0,
      "panic_sites": 0,
      "unwrap_calls": 0,
      "allocation_sites": 0,
      "io_operations": 2,
      "threading_constructs": 0
    },
    {
      "file_path": "src/abi/Types.idr",
      "lines": 231,
      "unsafe_blocks": 1,
      "panic_sites": 0,
      "unwrap_calls": 0,
      "allocation_sites": 0,
      "io_operations": 0,
      "threading_constructs": 0
    },
    {
      "file_path": "src/abi/Foreign.idr",
      "lines": 216,
      "unsafe_blocks": 12,
      "panic_sites": 0,
      "unwrap_calls": 0,
      "allocation_sites": 0,
      "io_operations": 0,
      "threading_constructs": 0
    },
    {
      "file_path": "contrastive_model.jl",
      "lines": 1535,
      "unsafe_blocks": 0,
      "panic_sites": 0,
      "unwrap_calls": 0,
      "allocation_sites": 0,
      "io_operations": 1,
      "threading_constructs": 0
    },
    {
      "file_path": "julia_utils.jl",
      "lines": 943,
      "unsafe_blocks": 0,
      "panic_sites": 0,
      "unwrap_calls": 0,
      "allocation_sites": 10,
      "io_operations": 2,
      "threading_constructs": 0
    },
    {
      "file_path": "contractiles/trust/Trustfile.hs",
      "lines": 105,
      "unsafe_blocks": 0,
      "panic_sites": 0,
      "unwrap_calls": 0,
      "allocation_sites": 0,
      "io_operations": 1,
      "threading_constructs": 0
    },
    {
      "file_path": "ffi/zig/src/main.zig",
      "lines": 274,
      "unsafe_blocks": 0,
      "panic_sites": 0,
      "unwrap_calls": 0,
      "allocation_sites": 1,
      "io_operations": 0,
      "threading_constructs": 0
    },
    {
      "file_path": "ffi/zig/test/integration_test.zig",
      "lines": 182,
      "unsafe_blocks": 0,
      "panic_sites": 0,
      "unwrap_calls": 0,
      "allocation_sites": 0,
      "io_operations": 0,
      "threading_constructs": 2
    }
  ],
  "recommended_attacks": [
    "disk",
    "memory",
    "cpu"
  ],
  "dependency_graph": {
    "edges": [
      {
        "from": "src/main.rs",
        "to": "src/metadata.rs",
        "relation": "shared_dir:src",
        "weight": 1.0
      },
      {
        "from": "src/abi/Types.idr",
        "to": "src/abi/Foreign.idr",
        "relation": "shared_dir:src/abi",
        "weight": 1.0
      },
      {
        "from": "contrastive_model.jl",
        "to": "julia_utils.jl",
        "relation": "shared_dir:",
        "weight": 1.0
      },
      {
        "from": "src/main.rs",
        "to": "Concurrent",
        "relation": "framework",
        "weight": 4.0
      },
      {
        "from": "src/metadata.rs",
        "to": "Concurrent",
        "relation": "framework",
        "weight": 1.0
      },
      {
        "from": "src/abi/Types.idr",
        "to": "Concurrent",
        "relation": "framework",
        "weight": 3.0
      },
      {
        "from": "src/abi/Foreign.idr",
        "to": "Concurrent",
        "relation": "framework",
        "weight": 36.0
      },
      {
        "from": "contrastive_model.jl",
        "to": "Concurrent",
        "relation": "framework",
        "weight": 1.0
      },
      {
        "from": "julia_utils.jl",
        "to": "Concurrent",
        "relation": "framework",
        "weight": 1.0
      },
      {
        "from": "contractiles/trust/Trustfile.hs",
        "to": "Concurrent",
        "relation": "framework",
        "weight": 1.0
      },
      {
        "from": "ffi/zig/src/main.zig",
        "to": "Concurrent",
        "relation": "framework",
        "weight": 1.0
      },
      {
        "from": "ffi/zig/test/integration_test.zig",
        "to": "Concurrent",
        "relation": "framework",
        "weight": 4.0
      }
    ]
  },
  "taint_matrix": {
    "rows": []
  }
}